LICENSE
MANIFEST.in
README.rst
setup.py
bin/glin
glin/__main__.py
glin/animations.py
glin/app.py
glin/default.conf
glin/hwBackend.py
glin.egg-info/PKG-INFO
glin.egg-info/SOURCES.txt
glin.egg-info/dependency_links.txt
glin.egg-info/entry_points.txt
glin.egg-info/not-zip-safe
glin.egg-info/requires.txt
glin.egg-info/top_level.txt