Metadata-Version: 1.0
Name: glin
Version: 0.0.3
Summary: Manages animations for LED stripes
Home-page: http://github.com/zaturox/glin
Author: zaturox
Author-email: zaturox@noreply.github.com
License: LGPL
Platform: UNKNOWN
